github_projects_mcp/__init__.py
github_projects_mcp/github_client.py
github_projects_mcp/server.py
mcp_github_projects-0.3.0.dist-info/METADATA
mcp_github_projects-0.3.0.dist-info/WHEEL
mcp_github_projects-0.3.0.dist-info/entry_points.txt
mcp_github_projects-0.3.0.dist-info/licenses/LICENSE
mcp_github_projects-0.3.0.dist-info/RECORD
