Metadata-Version: 2.4
Name: mcp-github-projects
Version: 0.3.0
Summary: MCP Server for interacting with GitHub Projects V2
Project-URL: Homepage, https://github.com/Arclio/github-projects-mcp
Project-URL: Repository, https://github.com/Arclio/github-projects-mcp.git
Author-email: Hillary Kipkemoi <hillaryk2k@gmail.com>
License: MIT License
License-File: LICENSE
Requires-Python: ==3.12.8
Requires-Dist: fastmcp>=2.2.0
Requires-Dist: httpx>=0.27.0
